{"source_file":"./2_theo_42.wav","sample_rate":8000,"bits":16,"samples_per_pixel":5,"time_duration":0.264,"processed_time_duration":0.5004739336492892,"samples_length":422,"samples":[{"min":-10,"max":12,"rms":7.169379},{"min":-6,"max":17,"rms":10.139033},{"min":-6,"max":13,"rms":8.6602545},{"min":-11,"max":14,"rms":10.56409},{"min":-19,"max":26,"rms":19.77372},{"min":-21,"max":20,"rms":18.963121},{"min":-16,"max":17,"rms":12.385475},{"min":-48,"max":66,"rms":42.220848},{"min":-184,"max":477,"rms":237.21889},{"min":-243,"max":123,"rms":154.35219},{"min":-99,"max":57,"rms":62.194855},{"min":-12,"max":23,"rms":12.157303},{"min":-18,"max":66,"rms":34.31909},{"min":-56,"max":63,"rms":40.32369},{"min":-73,"max":52,"rms":57.120926},{"min":-44,"max":60,"rms":35.516193},{"min":-20,"max":14,"rms":11.532562},{"min":-75,"max":66,"rms":52.44807},{"min":-167,"max":738,"rms":353.3743},{"min":-267,"max":1,"rms":144.00278},{"min":-215,"max":60,"rms":142.68146},{"min":-30,"max":200,"rms":106.16779},{"min":-259,"max":261,"rms":219.01004},{"min":-320,"max":316,"rms":243.16702},{"min":-380,"max":306,"rms":302.46124},{"min":-147,"max":200,"rms":121.226234},{"min":-236,"max":226,"rms":211.17433},{"min":-214,"max":143,"rms":132.8533},{"min":-90,"max":117,"rms":74.94798},{"min":-203,"max":163,"rms":126.80457},{"min":-144,"max":413,"rms":245.80765},{"min":-238,"max":0,"rms":152.5844},{"min":-263,"max":162,"rms":145.77106},{"min":-346,"max":673,"rms":364.5839},{"min":-303,"max":248,"rms":217.41205},{"min":-266,"max":8,"rms":148.35498},{"min":-107,"max":137,"rms":89.45613},{"min":-135,"max":261,"rms":164.17673},{"min":-362,"max":167,"rms":218.76471},{"min":-306,"max":212,"rms":184.7344},{"min":-33,"max":233,"rms":105.64753},{"min":-196,"max":246,"rms":184.34857},{"min":-239,"max":195,"rms":148.0},{"min":-79,"max":169,"rms":92.19111},{"min":-275,"max":121,"rms":152.14992},{"min":-125,"max":137,"rms":108.58821},{"min":-191,"max":226,"rms":149.98},{"min":-234,"max":141,"rms":143.45242},{"min":-232,"max":128,"rms":121.01074},{"min":-272,"max":225,"rms":163.7889},{"min":-266,"max":277,"rms":232.76212},{"min":-220,"max":159,"rms":157.21513},{"min":-148,"max":164,"rms":115.13036},{"min":-78,"max":169,"rms":100.03999},{"min":-160,"max":189,"rms":127.26822},{"min":-116,"max":88,"rms":72.4831},{"min":-205,"max":314,"rms":176.55934},{"min":-95,"max":124,"rms":76.86221},{"min":-102,"max":30,"rms":51.123383},{"min":-46,"max":37,"rms":37.202152},{"min":-83,"max":118,"rms":96.679886},{"min":-123,"max":75,"rms":67.687515},{"min":-173,"max":95,"rms":93.65789},{"min":-242,"max":223,"rms":179.95999},{"min":-180,"max":130,"rms":114.39056},{"min":-139,"max":138,"rms":120.75595},{"min":-119,"max":76,"rms":69.4291},{"min":-167,"max":174,"rms":121.9959},{"min":-275,"max":258,"rms":239.86789},{"min":-239,"max":163,"rms":179.13515},{"min":-375,"max":372,"rms":269.91406},{"min":-183,"max":334,"rms":211.76495},{"min":-120,"max":91,"rms":86.77557},{"min":-77,"max":140,"rms":79.70194},{"min":-112,"max":77,"rms":65.81641},{"min":-157,"max":103,"rms":103.56351},{"min":-136,"max":195,"rms":108.22107},{"min":-147,"max":158,"rms":112.22032},{"min":-108,"max":134,"rms":110.5423},{"min":-220,"max":219,"rms":180.53366},{"min":-160,"max":72,"rms":84.61206},{"min":-239,"max":194,"rms":148.32195},{"min":-125,"max":189,"rms":102.92716},{"min":-86,"max":66,"rms":62.702473},{"min":-116,"max":75,"rms":66.71132},{"min":-44,"max":26,"rms":26.408333},{"min":-149,"max":193,"rms":147.38385},{"min":-76,"max":66,"rms":53.295403},{"min":-89,"max":102,"rms":73.16147},{"min":-76,"max":46,"rms":46.270943},{"min":-74,"max":46,"rms":48.674427},{"min":-81,"max":107,"rms":77.57706},{"min":-202,"max":138,"rms":121.73003},{"min":-102,"max":96,"rms":64.051544},{"min":-229,"max":237,"rms":184.73766},{"min":-125,"max":148,"rms":97.34475},{"min":-243,"max":183,"rms":185.62543},{"min":-98,"max":51,"rms":54.092514},{"min":-132,"max":138,"rms":111.19892},{"min":-51,"max":38,"rms":39.28104},{"min":-46,"max":59,"rms":38.491558},{"min":-139,"max":161,"rms":111.99554},{"min":-128,"max":104,"rms":87.15159},{"min":-144,"max":189,"rms":120.05249},{"min":-61,"max":98,"rms":60.855564},{"min":-119,"max":85,"rms":82.19489},{"min":-114,"max":138,"rms":81.8975},{"min":-241,"max":182,"rms":154.34183},{"min":-162,"max":192,"rms":129.8345},{"min":-95,"max":115,"rms":84.11302},{"min":-152,"max":208,"rms":126.76987},{"min":-93,"max":61,"rms":65.453804},{"min":-29,"max":72,"rms":48.36321},{"min":-35,"max":65,"rms":34.06758},{"min":-71,"max":20,"rms":36.188396},{"min":-116,"max":107,"rms":85.04469},{"min":-42,"max":25,"rms":24.392622},{"min":-137,"max":132,"rms":103.55868},{"min":-101,"max":36,"rms":53.89434},{"min":-162,"max":144,"rms":116.81181},{"min":-113,"max":170,"rms":100.08197},{"min":-102,"max":116,"rms":89.62031},{"min":-103,"max":86,"rms":85.73681},{"min":-67,"max":75,"rms":48.18091},{"min":-11,"max":88,"rms":42.059483},{"min":-82,"max":75,"rms":74.087784},{"min":-6,"max":119,"rms":56.25122},{"min":-89,"max":93,"rms":70.40739},{"min":-121,"max":0,"rms":63.693012},{"min":-145,"max":0,"rms":114.10872},{"min":-119,"max":23,"rms":75.50364},{"min":-19,"max":139,"rms":98.5931},{"min":0,"max":170,"rms":126.98346},{"min":0,"max":77,"rms":52.77689},{"min":0,"max":55,"rms":44.75042},{"min":0,"max":103,"rms":63.27559},{"min":-154,"max":92,"rms":113.20071},{"min":-292,"max":0,"rms":254.54115},{"min":-376,"max":0,"rms":256.90582},{"min":-99,"max":163,"rms":104.53707},{"min":0,"max":419,"rms":347.02304},{"min":0,"max":289,"rms":234.27762},{"min":0,"max":196,"rms":102.62066},{"min":0,"max":115,"rms":89.36554},{"min":-314,"max":63,"rms":169.35583},{"min":-542,"max":0,"rms":486.30588},{"min":-580,"max":0,"rms":501.67978},{"min":-164,"max":559,"rms":292.73947},{"min":0,"max":820,"rms":752.9296},{"min":0,"max":595,"rms":367.82196},{"min":-289,"max":0,"rms":197.4467},{"min":-118,"max":209,"rms":130.51514},{"min":-21,"max":311,"rms":218.65771},{"min":-874,"max":0,"rms":602.1161},{"min":-808,"max":0,"rms":717.24945},{"min":-504,"max":670,"rms":389.64163},{"min":0,"max":1060,"rms":935.20044},{"min":-92,"max":757,"rms":449.43274},{"min":-620,"max":0,"rms":496.06876},{"min":-365,"max":382,"rms":287.41678},{"min":0,"max":607,"rms":480.62357},{"min":-827,"max":175,"rms":550.9381},{"min":-1034,"max":0,"rms":844.84045},{"min":-639,"max":232,"rms":410.6575},{"min":0,"max":1002,"rms":832.0603},{"min":0,"max":994,"rms":669.6602},{"min":-707,"max":0,"rms":530.88605},{"min":-493,"max":348,"rms":324.07715},{"min":0,"max":742,"rms":638.7026},{"min":-392,"max":542,"rms":331.90118},{"min":-1082,"max":0,"rms":954.60675},{"min":-897,"max":0,"rms":623.7602},{"min":-37,"max":963,"rms":589.71027},{"min":0,"max":982,"rms":840.921},{"min":-615,"max":335,"rms":342.43015},{"min":-644,"max":0,"rms":524.90015},{"min":0,"max":820,"rms":554.3672},{"min":0,"max":727,"rms":547.3774},{"min":-1085,"max":0,"rms":664.94574},{"min":-1072,"max":0,"rms":839.9169},{"min":-429,"max":152,"rms":272.63235},{"min":0,"max":905,"rms":671.4755},{"min":0,"max":888,"rms":584.81824},{"min":-609,"max":0,"rms":407.72293},{"min":-517,"max":398,"rms":404.76733},{"min":0,"max":871,"rms":675.60785},{"min":-383,"max":560,"rms":382.5585},{"min":-1055,"max":0,"rms":805.1769},{"min":-742,"max":0,"rms":615.47363},{"min":-296,"max":145,"rms":190.92564},{"min":0,"max":901,"rms":690.35455},{"min":-23,"max":739,"rms":452.30188},{"min":-556,"max":0,"rms":381.57306},{"min":-523,"max":318,"rms":344.42502},{"min":0,"max":855,"rms":684.45013},{"min":-390,"max":324,"rms":311.5426},{"min":-794,"max":0,"rms":662.85034},{"min":-751,"max":0,"rms":487.4657},{"min":-180,"max":93,"rms":116.437965},{"min":0,"max":737,"rms":429.63937},{"min":0,"max":745,"rms":493.36316},{"min":-414,"max":6,"rms":238.65163},{"min":-396,"max":87,"rms":271.8746},{"min":0,"max":588,"rms":464.778},{"min":-44,"max":686,"rms":368.71616},{"min":-576,"max":0,"rms":396.18378},{"min":-582,"max":0,"rms":454.72388},{"min":-287,"max":0,"rms":218.37308},{"min":-254,"max":393,"rms":223.86916},{"min":0,"max":704,"rms":542.6091},{"min":0,"max":474,"rms":307.86035},{"min":-500,"max":0,"rms":353.50076},{"min":-473,"max":116,"rms":235.11996},{"min":0,"max":710,"rms":581.54675},{"min":-153,"max":565,"rms":286.1737},{"min":-480,"max":0,"rms":398.9085},{"min":-409,"max":0,"rms":284.33008},{"min":-324,"max":0,"rms":244.34361},{"min":-380,"max":234,"rms":306.7983},{"min":0,"max":729,"rms":526.8341},{"min":0,"max":470,"rms":349.34625},{"min":-453,"max":0,"rms":341.06393},{"min":-446,"max":133,"rms":217.20313},{"min":0,"max":661,"rms":532.3418},{"min":-87,"max":476,"rms":303.68008},{"min":-368,"max":0,"rms":293.72504},{"min":-285,"max":0,"rms":196.64384},{"min":-347,"max":0,"rms":269.02863},{"min":-548,"max":0,"rms":491.5978},{"min":-222,"max":554,"rms":356.71838},{"min":0,"max":795,"rms":644.8324},{"min":-349,"max":250,"rms":258.08487},{"min":-459,"max":0,"rms":351.88153},{"min":0,"max":439,"rms":327.00488},{"min":0,"max":553,"rms":418.86847},{"min":-245,"max":130,"rms":182.03241},{"min":-236,"max":0,"rms":170.5151},{"min":-247,"max":16,"rms":117.52361},{"min":-596,"max":0,"rms":448.83005},{"min":-584,"max":0,"rms":451.60913},{"min":-95,"max":641,"rms":457.20346},{"min":0,"max":899,"rms":675.3041},{"min":-404,"max":212,"rms":266.80966},{"min":-501,"max":0,"rms":368.17874},{"min":0,"max":471,"rms":303.51376},{"min":0,"max":372,"rms":323.60657},{"min":-329,"max":0,"rms":162.69296},{"min":-307,"max":0,"rms":152.8411},{"min":0,"max":195,"rms":147.91147},{"min":-395,"max":59,"rms":260.94904},{"min":-621,"max":0,"rms":565.97314},{"min":-462,"max":88,"rms":312.55142},{"min":0,"max":766,"rms":576.4097},{"min":0,"max":763,"rms":464.91675},{"min":-378,"max":0,"rms":297.84525},{"min":-403,"max":50,"rms":261.764},{"min":0,"max":383,"rms":275.225},{"min":0,"max":276,"rms":208.17397},{"min":-25,"max":22,"rms":18.57956},{"min":-9,"max":164,"rms":110.3005},{"min":-22,"max":211,"rms":122.982925},{"min":-604,"max":0,"rms":413.07022},{"min":-658,"max":0,"rms":547.0797},{"min":-340,"max":44,"rms":195.03947},{"min":0,"max":525,"rms":360.5235},{"min":0,"max":374,"rms":306.31747},{"min":-162,"max":25,"rms":100.65287},{"min":-163,"max":2,"rms":106.509155},{"min":0,"max":239,"rms":179.54832},{"min":-6,"max":199,"rms":126.44287},{"min":-71,"max":2,"rms":56.01607},{"min":0,"max":259,"rms":167.88985},{"min":0,"max":270,"rms":227.8201},{"min":-292,"max":47,"rms":178.11963},{"min":-457,"max":0,"rms":436.0133},{"min":-472,"max":0,"rms":352.7716},{"min":-159,"max":0,"rms":80.0937},{"min":0,"max":76,"rms":48.394215},{"min":0,"max":298,"rms":253.08575},{"min":0,"max":377,"rms":284.72162},{"min":-125,"max":136,"rms":92.429436},{"min":-160,"max":0,"rms":140.85808},{"min":-41,"max":124,"rms":74.80909},{"min":0,"max":202,"rms":187.21593},{"min":0,"max":176,"rms":142.61346},{"min":-25,"max":78,"rms":49.199593},{"min":-134,"max":0,"rms":101.297585},{"min":-241,"max":0,"rms":214.27786},{"min":-299,"max":0,"rms":274.59644},{"min":-237,"max":0,"rms":162.62657},{"min":-34,"max":78,"rms":59.608723},{"min":-12,"max":69,"rms":40.405445},{"min":-11,"max":146,"rms":98.56064},{"min":0,"max":247,"rms":196.56805},{"min":-33,"max":129,"rms":93.60663},{"min":-54,"max":0,"rms":39.69383},{"min":-6,"max":55,"rms":37.0756},{"min":0,"max":102,"rms":88.87407},{"min":0,"max":105,"rms":89.96777},{"min":-6,"max":56,"rms":46.931866},{"min":-152,"max":0,"rms":95.07471},{"min":-220,"max":0,"rms":200.65244},{"min":-216,"max":0,"rms":176.1153},{"min":-145,"max":0,"rms":114.73012},{"min":-79,"max":0,"rms":41.876007},{"min":0,"max":59,"rms":48.303207},{"min":0,"max":153,"rms":105.75065},{"min":0,"max":224,"rms":202.8354},{"min":0,"max":177,"rms":119.93998},{"min":-104,"max":0,"rms":69.887054},{"min":-81,"max":0,"rms":56.59682},{"min":-9,"max":28,"rms":18.836136},{"min":0,"max":20,"rms":15.251229},{"min":0,"max":106,"rms":92.59266},{"min":0,"max":103,"rms":70.084236},{"min":-151,"max":0,"rms":99.72964},{"min":-175,"max":0,"rms":156.37007},{"min":-138,"max":0,"rms":103.11838},{"min":-62,"max":0,"rms":35.207954},{"min":-11,"max":10,"rms":8.3666},{"min":-21,"max":13,"rms":12.680695},{"min":0,"max":181,"rms":129.5191},{"min":0,"max":166,"rms":133.37317},{"min":-124,"max":29,"rms":92.6747},{"min":-143,"max":0,"rms":112.41352},{"min":0,"max":149,"rms":98.60324},{"min":0,"max":145,"rms":121.136284},{"min":0,"max":86,"rms":71.66589},{"min":0,"max":45,"rms":38.015785},{"min":-71,"max":6,"rms":51.017643},{"min":-184,"max":0,"rms":153.47508},{"min":-148,"max":0,"rms":128.93874},{"min":-71,"max":7,"rms":39.461372},{"min":-17,"max":50,"rms":33.13608},{"min":-68,"max":0,"rms":55.92137},{"min":-72,"max":15,"rms":50.62608},{"min":0,"max":133,"rms":102.134224},{"min":0,"max":116,"rms":94.56532},{"min":-5,"max":30,"rms":15.880806},{"min":0,"max":59,"rms":34.275356},{"min":0,"max":76,"rms":70.45424},{"min":0,"max":49,"rms":41.87123},{"min":-8,"max":41,"rms":25.24282},{"min":-41,"max":0,"rms":23.242203},{"min":-54,"max":0,"rms":46.23202},{"min":-65,"max":0,"rms":52.331635},{"min":-122,"max":0,"rms":98.985855},{"min":-129,"max":0,"rms":111.691536},{"min":-70,"max":0,"rms":53.34229},{"min":0,"max":37,"rms":25.119713},{"min":0,"max":91,"rms":83.26704},{"min":0,"max":101,"rms":86.46618},{"min":0,"max":64,"rms":54.01111},{"min":0,"max":59,"rms":37.75182},{"min":-27,"max":0,"rms":17.680498},{"min":-17,"max":39,"rms":21.241468},{"min":0,"max":113,"rms":96.63747},{"min":0,"max":99,"rms":63.017456},{"min":-84,"max":0,"rms":64.686935},{"min":-121,"max":0,"rms":108.0907},{"min":-107,"max":0,"rms":89.55334},{"min":-113,"max":0,"rms":91.12958},{"min":-63,"max":13,"rms":43.714985},{"min":0,"max":84,"rms":60.48967},{"min":0,"max":98,"rms":89.5243},{"min":0,"max":74,"rms":58.84046},{"min":-11,"max":22,"rms":13.906833},{"min":-50,"max":17,"rms":34.04409},{"min":0,"max":30,"rms":19.131126},{"min":0,"max":51,"rms":33.331665},{"min":0,"max":52,"rms":35.938835},{"min":0,"max":74,"rms":57.42125},{"min":-15,"max":38,"rms":21.142374},{"min":-112,"max":0,"rms":94.694244},{"min":-88,"max":0,"rms":76.46437},{"min":-56,"max":0,"rms":40.0025},{"min":-55,"max":0,"rms":32.572994},{"min":-29,"max":27,"rms":20.933228},{"min":-19,"max":35,"rms":24.41311},{"min":-12,"max":3,"rms":6.308724},{"min":-36,"max":12,"rms":18.35756},{"min":0,"max":69,"rms":52.988678},{"min":-1,"max":30,"rms":14.0285425},{"min":0,"max":38,"rms":23.63895},{"min":0,"max":60,"rms":48.42107},{"min":0,"max":75,"rms":51.712666},{"min":0,"max":57,"rms":28.209927},{"min":-62,"max":0,"rms":44.070396},{"min":-71,"max":0,"rms":53.975918},{"min":-86,"max":0,"rms":67.70968},{"min":-70,"max":0,"rms":45.86502},{"min":-16,"max":5,"rms":9.899495},{"min":-14,"max":22,"rms":13.579396},{"min":-18,"max":0,"rms":15.735311},{"min":0,"max":16,"rms":11.63615},{"min":0,"max":37,"rms":26.668333},{"min":0,"max":38,"rms":25.577333},{"min":0,"max":82,"rms":52.15937},{"min":0,"max":104,"rms":80.17855},{"min":-1,"max":37,"rms":22.521101},{"min":-28,"max":15,"rms":16.958775},{"min":-54,"max":0,"rms":49.187397},{"min":-54,"max":0,"rms":40.980484},{"min":-70,"max":0,"rms":52.79015},{"min":-74,"max":0,"rms":58.336952},{"min":-67,"max":15,"rms":35.80782},{"min":0,"max":31,"rms":20.46949},{"min":-34,"max":0,"rms":19.909796},{"min":-7,"max":25,"rms":13.183323},{"min":0,"max":93,"rms":73.89046},{"min":0,"max":63,"rms":34.5948},{"min":0,"max":44,"rms":31.808804},{"min":0,"max":59,"rms":46.458584},{"min":0,"max":27,"rms":21.563858},{"min":-33,"max":2,"rms":16.727222},{"min":-39,"max":0,"rms":33.093807},{"min":-47,"max":0,"rms":37.196774},{"min":-43,"max":0,"rms":32.33574},{"min":-48,"max":0,"rms":30.864218},{"min":-49,"max":0,"rms":32.69251},{"min":-25,"max":5,"rms":11.61034},{"min":-21,"max":3,"rms":13.520355}]}