{"source_file":"./8_theo_30.wav","sample_rate":8000,"bits":16,"samples_per_pixel":256,"time_duration":0.4065,"processed_time_duration":27.099999999999999,"samples_length":12,"samples":[{"min":-3009,"max":4854,"rms":1239.3978},{"min":-4230,"max":9594,"rms":2948.36},{"min":-4564,"max":9082,"rms":3132.0232},{"min":-4658,"max":7955,"rms":2287.7795},{"min":-1882,"max":1996,"rms":801.48566},{"min":-968,"max":1043,"rms":320.60614},{"min":-312,"max":410,"rms":111.02759},{"min":-213,"max":297,"rms":68.164154},{"min":-69,"max":69,"rms":25.724503},{"min":-548,"max":781,"rms":149.64609},{"min":-521,"max":490,"rms":180.66594},{"min":-277,"max":294,"rms":82.56664}]}