{"source_file":"./3_yweweler_16.wav","sample_rate":8000,"bits":16,"samples_per_pixel":256,"time_duration":0.3485,"processed_time_duration":27.88,"samples_length":10,"samples":[{"min":-27,"max":31,"rms":9.032926},{"min":-1663,"max":1253,"rms":477.1199},{"min":-2156,"max":1601,"rms":877.40594},{"min":-2432,"max":1624,"rms":878.5499},{"min":-1894,"max":1145,"rms":554.8431},{"min":-1027,"max":636,"rms":313.54123},{"min":-359,"max":234,"rms":108.85681},{"min":-114,"max":81,"rms":39.126396},{"min":-59,"max":63,"rms":21.750898},{"min":-51,"max":52,"rms":19.891306}]}