{"source_file":"./1_yweweler_38.wav","sample_rate":8000,"bits":16,"samples_per_pixel":5,"time_duration":0.367625,"processed_time_duration":0.5001700680272109,"samples_length":588,"samples":[{"min":-19,"max":0,"rms":14.205633},{"min":-27,"max":0,"rms":25.841825},{"min":-26,"max":0,"rms":19.692638},{"min":-8,"max":6,"rms":5.347897},{"min":0,"max":24,"rms":17.561321},{"min":0,"max":31,"rms":27.162474},{"min":0,"max":22,"rms":17.86057},{"min":-1,"max":11,"rms":6.4187226},{"min":-5,"max":2,"rms":3.1622777},{"min":-4,"max":0,"rms":3.193744},{"min":-16,"max":0,"rms":9.273619},{"min":-44,"max":0,"rms":36.381313},{"min":-47,"max":0,"rms":39.405582},{"min":-21,"max":3,"rms":13.704014},{"min":0,"max":52,"rms":33.674915},{"min":0,"max":53,"rms":46.465042},{"min":0,"max":24,"rms":17.714401},{"min":0,"max":11,"rms":7.4161983},{"min":0,"max":9,"rms":6.180615},{"min":-2,"max":9,"rms":5.196152},{"min":-105,"max":0,"rms":80.96419},{"min":-333,"max":0,"rms":244.51625},{"min":-343,"max":0,"rms":284.73425},{"min":-127,"max":0,"rms":91.09336},{"min":-77,"max":82,"rms":61.297634},{"min":0,"max":327,"rms":277.01407},{"min":0,"max":251,"rms":161.8487},{"min":0,"max":166,"rms":143.14328},{"min":0,"max":113,"rms":65.41406},{"min":0,"max":56,"rms":39.862263},{"min":-21,"max":35,"rms":20.332241},{"min":-39,"max":0,"rms":29.529646},{"min":-241,"max":4,"rms":113.584335},{"min":-404,"max":0,"rms":363.8879},{"min":-339,"max":0,"rms":236.69981},{"min":0,"max":100,"rms":68.50548},{"min":-63,"max":0,"rms":39.05893},{"min":0,"max":165,"rms":118.27764},{"min":0,"max":175,"rms":161.62859},{"min":0,"max":220,"rms":212.1457},{"min":0,"max":184,"rms":109.13661},{"min":-5,"max":28,"rms":16.124516},{"min":0,"max":40,"rms":36.127552},{"min":0,"max":23,"rms":16.917446},{"min":0,"max":129,"rms":78.50987},{"min":-641,"max":0,"rms":492.1199},{"min":-557,"max":0,"rms":380.31775},{"min":-31,"max":176,"rms":138.80202},{"min":0,"max":176,"rms":107.30704},{"min":-43,"max":29,"rms":30.463093},{"min":-35,"max":148,"rms":77.03376},{"min":0,"max":296,"rms":262.71963},{"min":0,"max":194,"rms":131.37427},{"min":-20,"max":40,"rms":25.274492},{"min":-22,"max":58,"rms":35.15395},{"min":0,"max":61,"rms":51.224995},{"min":0,"max":51,"rms":42.63332},{"min":-42,"max":115,"rms":90.58256},{"min":-743,"max":0,"rms":558.4566},{"min":-661,"max":0,"rms":443.75107},{"min":0,"max":254,"rms":201.2973},{"min":0,"max":217,"rms":153.98961},{"min":-171,"max":22,"rms":115.71862},{"min":-147,"max":292,"rms":171.6543},{"min":0,"max":395,"rms":324.3896},{"min":0,"max":147,"rms":91.56746},{"min":-73,"max":0,"rms":54.404045},{"min":-53,"max":100,"rms":63.483856},{"min":0,"max":119,"rms":90.72486},{"min":0,"max":35,"rms":19.49359},{"min":0,"max":80,"rms":51.726204},{"min":-597,"max":0,"rms":361.1684},{"min":-656,"max":0,"rms":558.325},{"min":-155,"max":231,"rms":174.56174},{"min":0,"max":248,"rms":193.77771},{"min":-134,"max":83,"rms":81.55489},{"min":-149,"max":144,"rms":117.51681},{"min":0,"max":375,"rms":333.98172},{"min":0,"max":277,"rms":157.86197},{"min":-58,"max":0,"rms":34.099854},{"min":-60,"max":99,"rms":60.36224},{"min":0,"max":154,"rms":132.08255},{"min":-36,"max":46,"rms":28.376047},{"min":-28,"max":129,"rms":62.689713},{"min":-411,"max":161,"rms":222.1873},{"min":-792,"max":0,"rms":721.035},{"min":-408,"max":327,"rms":266.19504},{"min":0,"max":337,"rms":266.79132},{"min":-63,"max":145,"rms":95.04525},{"min":-287,"max":0,"rms":234.29681},{"min":0,"max":516,"rms":374.92667},{"min":0,"max":460,"rms":279.60614},{"min":-72,"max":0,"rms":58.153248},{"min":-55,"max":47,"rms":42.350914},{"min":0,"max":227,"rms":190.85701},{"min":-45,"max":157,"rms":82.36868},{"min":-53,"max":14,"rms":37.65634},{"min":0,"max":160,"rms":107.07007},{"min":-730,"max":0,"rms":514.4391},{"min":-751,"max":0,"rms":524.9381},{"min":0,"max":306,"rms":254.79364},{"min":0,"max":197,"rms":155.84287},{"min":-358,"max":117,"rms":208.51234},{"min":-430,"max":286,"rms":298.58264},{"min":0,"max":625,"rms":519.89136},{"min":-127,"max":123,"rms":101.86756},{"min":0,"max":98,"rms":73.5894},{"min":0,"max":192,"rms":105.85556},{"min":0,"max":280,"rms":228.19377},{"min":-175,"max":2,"rms":128.52548},{"min":-140,"max":76,"rms":84.90347},{"min":-212,"max":213,"rms":158.20177},{"min":-798,"max":0,"rms":700.92096},{"min":-562,"max":305,"rms":324.84518},{"min":0,"max":351,"rms":265.01624},{"min":0,"max":114,"rms":97.90404},{"min":-450,"max":0,"rms":341.0352},{"min":-288,"max":636,"rms":388.6083},{"min":-49,"max":679,"rms":440.50946},{"min":-218,"max":56,"rms":150.9914},{"min":0,"max":135,"rms":125.30842},{"min":0,"max":288,"rms":243.69078},{"min":-194,"max":199,"rms":141.68839},{"min":-228,"max":0,"rms":164.37093},{"min":0,"max":234,"rms":165.65627},{"min":-660,"max":255,"rms":364.07416},{"min":-974,"max":0,"rms":824.6073},{"min":-138,"max":476,"rms":348.47495},{"min":-27,"max":355,"rms":195.44002},{"min":-137,"max":27,"rms":63.21234},{"min":-479,"max":0,"rms":361.6573},{"min":0,"max":775,"rms":588.11224},{"min":-320,"max":489,"rms":301.25137},{"min":-271,"max":301,"rms":214.42528},{"min":0,"max":326,"rms":225.60762},{"min":0,"max":158,"rms":136.76038},{"min":-212,"max":0,"rms":157.03885},{"min":-127,"max":170,"rms":118.91762},{"min":0,"max":168,"rms":131.82791},{"min":-771,"max":125,"rms":433.0986},{"min":-969,"max":0,"rms":769.06934},{"min":0,"max":544,"rms":422.8643},{"min":-198,"max":165,"rms":150.41144},{"min":-123,"max":73,"rms":74.02162},{"min":-386,"max":10,"rms":291.23495},{"min":0,"max":699,"rms":569.0016},{"min":-290,"max":252,"rms":220.22626},{"min":-87,"max":345,"rms":253.79204},{"min":0,"max":294,"rms":176.11076},{"min":-17,"max":106,"rms":80.59405},{"min":-97,"max":0,"rms":80.3231},{"min":-30,"max":45,"rms":30.825314},{"min":0,"max":154,"rms":112.243485},{"min":-828,"max":164,"rms":467.65073},{"min":-931,"max":0,"rms":696.45715},{"min":0,"max":448,"rms":334.63623},{"min":-168,"max":0,"rms":119.78982},{"min":-83,"max":115,"rms":77.50097},{"min":-315,"max":35,"rms":245.3793},{"min":0,"max":576,"rms":478.27167},{"min":-218,"max":197,"rms":171.26529},{"min":-58,"max":333,"rms":238.23434},{"min":0,"max":293,"rms":188.65152},{"min":-15,"max":113,"rms":82.37718},{"min":-71,"max":0,"rms":48.511852},{"min":-5,"max":11,"rms":6.6332498},{"min":-12,"max":147,"rms":75.772026},{"min":-754,"max":238,"rms":395.74258},{"min":-1047,"max":0,"rms":805.2849},{"min":0,"max":468,"rms":356.3456},{"min":-202,"max":0,"rms":139.92427},{"min":-77,"max":170,"rms":125.96984},{"min":-325,"max":0,"rms":241.50941},{"min":0,"max":492,"rms":398.77438},{"min":-134,"max":198,"rms":120.44999},{"min":0,"max":277,"rms":204.52286},{"min":0,"max":226,"rms":157.20941},{"min":-32,"max":137,"rms":97.70875},{"min":-103,"max":92,"rms":82.68132},{"min":-28,"max":121,"rms":87.65729},{"min":-56,"max":142,"rms":80.7044},{"min":-776,"max":241,"rms":417.64148},{"min":-1094,"max":0,"rms":847.53973},{"min":0,"max":515,"rms":372.06238},{"min":-257,"max":57,"rms":173.18199},{"min":-147,"max":224,"rms":168.23555},{"min":-156,"max":6,"rms":107.62341},{"min":0,"max":239,"rms":166.04337},{"min":-57,"max":298,"rms":184.96433},{"min":-76,"max":325,"rms":183.60283},{"min":0,"max":378,"rms":238.7794},{"min":-17,"max":111,"rms":73.13823},{"min":-54,"max":47,"rms":38.136597},{"min":-31,"max":144,"rms":93.02366},{"min":-133,"max":148,"rms":117.144356},{"min":-716,"max":358,"rms":399.58505},{"min":-1228,"max":0,"rms":951.8986},{"min":0,"max":560,"rms":392.49304},{"min":-240,"max":142,"rms":169.39008},{"min":-194,"max":243,"rms":172.35951},{"min":-136,"max":133,"rms":91.50629},{"min":-45,"max":258,"rms":134.3622},{"min":-204,"max":399,"rms":271.38388},{"min":-243,"max":457,"rms":281.19318},{"min":-70,"max":512,"rms":287.11774},{"min":-15,"max":230,"rms":167.40968},{"min":-149,"max":23,"rms":99.77475},{"min":-99,"max":168,"rms":121.999176},{"min":-148,"max":310,"rms":178.2156},{"min":-1037,"max":356,"rms":579.00653},{"min":-1368,"max":165,"rms":920.88525},{"min":-158,"max":574,"rms":381.27734},{"min":-208,"max":198,"rms":158.4178},{"min":-175,"max":144,"rms":136.91385},{"min":-149,"max":207,"rms":158.90816},{"min":-240,"max":430,"rms":268.67676},{"min":-284,"max":503,"rms":310.15286},{"min":-158,"max":512,"rms":361.9674},{"min":-148,"max":290,"rms":155.89291},{"min":-74,"max":361,"rms":249.9724},{"min":-255,"max":252,"rms":203.51659},{"min":-211,"max":304,"rms":200.8233},{"min":-203,"max":420,"rms":242.01198},{"min":-1506,"max":439,"rms":898.6549},{"min":-1283,"max":567,"rms":769.0139},{"min":-266,"max":567,"rms":315.81104},{"min":-47,"max":280,"rms":152.46835},{"min":-234,"max":312,"rms":197.10353},{"min":-471,"max":363,"rms":338.36636},{"min":-259,"max":708,"rms":498.34625},{"min":-413,"max":185,"rms":267.04608},{"min":-4,"max":565,"rms":399.54922},{"min":-184,"max":426,"rms":255.882},{"min":-208,"max":378,"rms":225.06577},{"min":0,"max":331,"rms":217.5408},{"min":-234,"max":170,"rms":163.46925},{"min":-313,"max":249,"rms":248.40451},{"min":-1371,"max":0,"rms":1020.47046},{"min":-233,"max":447,"rms":316.0076},{"min":-93,"max":81,"rms":60.57062},{"min":-100,"max":143,"rms":93.125725},{"min":-92,"max":292,"rms":169.10115},{"min":-410,"max":475,"rms":325.03845},{"min":-274,"max":579,"rms":363.4592},{"min":-196,"max":419,"rms":303.4228},{"min":-57,"max":266,"rms":133.99104},{"min":-130,"max":355,"rms":247.63239},{"min":-124,"max":254,"rms":173.90054},{"min":-120,"max":69,"rms":82.17786},{"min":0,"max":187,"rms":168.65764},{"min":-1677,"max":360,"rms":946.2343},{"min":-1427,"max":592,"rms":857.70123},{"min":-243,"max":640,"rms":336.86942},{"min":-216,"max":246,"rms":165.56448},{"min":-202,"max":292,"rms":211.98396},{"min":-332,"max":98,"rms":222.85152},{"min":-117,"max":530,"rms":374.66864},{"min":-283,"max":501,"rms":324.92862},{"min":-104,"max":371,"rms":196.34459},{"min":0,"max":354,"rms":254.9898},{"min":-1,"max":133,"rms":84.118965},{"min":-103,"max":179,"rms":96.704704},{"min":-62,"max":225,"rms":154.15901},{"min":-910,"max":468,"rms":512.2328},{"min":-1925,"max":376,"rms":1310.2552},{"min":-302,"max":758,"rms":489.35407},{"min":-166,"max":401,"rms":248.06088},{"min":-462,"max":567,"rms":394.99014},{"min":-579,"max":494,"rms":457.19907},{"min":-25,"max":637,"rms":459.91455},{"min":-281,"max":502,"rms":308.97055},{"min":-116,"max":457,"rms":231.35341},{"min":-55,"max":430,"rms":289.23727},{"min":-80,"max":361,"rms":241.14685},{"min":-225,"max":80,"rms":151.42192},{"min":-19,"max":332,"rms":232.41084},{"min":-1075,"max":488,"rms":571.6592},{"min":-2023,"max":315,"rms":1306.4596},{"min":-265,"max":735,"rms":410.81088},{"min":-250,"max":392,"rms":251.66843},{"min":-462,"max":576,"rms":420.3803},{"min":-502,"max":401,"rms":376.1505},{"min":-48,"max":327,"rms":233.3898},{"min":-62,"max":289,"rms":193.45387},{"min":0,"max":240,"rms":140.9468},{"min":0,"max":279,"rms":171.59604},{"min":0,"max":399,"rms":287.58408},{"min":-22,"max":111,"rms":68.23929},{"min":0,"max":287,"rms":179.94221},{"min":-1444,"max":354,"rms":847.01843},{"min":-1820,"max":376,"rms":1041.0925},{"min":-65,"max":221,"rms":130.5611},{"min":-336,"max":290,"rms":253.08101},{"min":-141,"max":446,"rms":280.70163},{"min":-298,"max":31,"rms":200.67188},{"min":0,"max":216,"rms":131.42982},{"min":0,"max":198,"rms":125.6328},{"min":0,"max":317,"rms":233.73404},{"min":0,"max":271,"rms":174.56346},{"min":0,"max":315,"rms":208.07547},{"min":0,"max":209,"rms":131.45113},{"min":0,"max":489,"rms":324.69278},{"min":-1756,"max":242,"rms":1335.8528},{"min":-718,"max":256,"rms":349.64868},{"min":-168,"max":344,"rms":225.12929},{"min":-314,"max":191,"rms":221.05113},{"min":0,"max":365,"rms":216.03981},{"min":-370,"max":31,"rms":219.81902},{"min":-134,"max":242,"rms":203.98431},{"min":-57,"max":341,"rms":219.17801},{"min":-2,"max":301,"rms":165.26645},{"min":0,"max":345,"rms":265.18976},{"min":-9,"max":255,"rms":166.0795},{"min":0,"max":305,"rms":201.9183},{"min":-512,"max":466,"rms":390.315},{"min":-1652,"max":0,"rms":1289.7885},{"min":-246,"max":163,"rms":184.73819},{"min":-305,"max":527,"rms":316.5928},{"min":-111,"max":249,"rms":158.5604},{"min":-286,"max":429,"rms":288.04617},{"min":-496,"max":500,"rms":360.95013},{"min":-177,"max":222,"rms":137.76646},{"min":0,"max":370,"rms":166.26845},{"min":0,"max":397,"rms":268.2238},{"min":-29,"max":432,"rms":316.95868},{"min":-66,"max":415,"rms":275.08798},{"min":-20,"max":500,"rms":241.56905},{"min":-1566,"max":584,"rms":1025.0184},{"min":-1198,"max":0,"rms":809.0393},{"min":-337,"max":446,"rms":314.01114},{"min":-106,"max":254,"rms":152.47623},{"min":-143,"max":303,"rms":158.05695},{"min":-383,"max":424,"rms":280.98328},{"min":-199,"max":171,"rms":161.49799},{"min":-35,"max":190,"rms":98.62556},{"min":-32,"max":308,"rms":214.59683},{"min":0,"max":311,"rms":254.73555},{"min":0,"max":217,"rms":169.82108},{"min":0,"max":154,"rms":128.27548},{"min":0,"max":249,"rms":203.715},{"min":-1202,"max":312,"rms":832.1597},{"min":-765,"max":0,"rms":585.1832},{"min":-77,"max":234,"rms":145.08342},{"min":0,"max":208,"rms":160.38641},{"min":-7,"max":156,"rms":102.412895},{"min":-292,"max":156,"rms":192.04323},{"min":-31,"max":106,"rms":66.7383},{"min":-109,"max":117,"rms":83.83675},{"min":0,"max":128,"rms":103.60888},{"min":0,"max":270,"rms":228.79466},{"min":0,"max":251,"rms":212.85442},{"min":0,"max":203,"rms":136.95328},{"min":0,"max":220,"rms":161.85179},{"min":-501,"max":6,"rms":422.4668},{"min":-711,"max":0,"rms":609.80945},{"min":-404,"max":0,"rms":256.18002},{"min":0,"max":249,"rms":184.67485},{"min":0,"max":231,"rms":197.01624},{"min":-119,"max":86,"rms":83.82243},{"min":0,"max":201,"rms":132.73131},{"min":0,"max":141,"rms":74.52919},{"min":-52,"max":40,"rms":33.896904},{"min":0,"max":121,"rms":107.7395},{"min":0,"max":256,"rms":225.76979},{"min":0,"max":198,"rms":165.31061},{"min":-1,"max":213,"rms":156.84387},{"min":-427,"max":0,"rms":364.3501},{"min":-647,"max":0,"rms":539.10516},{"min":-357,"max":0,"rms":248.47334},{"min":0,"max":240,"rms":166.75131},{"min":-18,"max":291,"rms":187.12456},{"min":0,"max":79,"rms":45.332108},{"min":0,"max":180,"rms":125.994446},{"min":0,"max":81,"rms":53.53317},{"min":-27,"max":39,"rms":27.316662},{"min":0,"max":171,"rms":101.888176},{"min":0,"max":203,"rms":192.31796},{"min":0,"max":171,"rms":135.09923},{"min":-59,"max":147,"rms":124.47169},{"min":-446,"max":0,"rms":348.5622},{"min":-619,"max":0,"rms":487.8219},{"min":-360,"max":8,"rms":229.93477},{"min":0,"max":232,"rms":152.24585},{"min":0,"max":255,"rms":164.75436},{"min":0,"max":60,"rms":41.835392},{"min":0,"max":128,"rms":96.383606},{"min":-30,"max":72,"rms":51.30497},{"min":-28,"max":49,"rms":33.73722},{"min":0,"max":168,"rms":100.158875},{"min":0,"max":210,"rms":196.88423},{"min":0,"max":198,"rms":144.18114},{"min":0,"max":103,"rms":87.24104},{"min":-367,"max":0,"rms":259.29095},{"min":-551,"max":0,"rms":454.889},{"min":-375,"max":0,"rms":264.85846},{"min":0,"max":146,"rms":97.46897},{"min":0,"max":234,"rms":171.24486},{"min":0,"max":69,"rms":51.11947},{"min":0,"max":126,"rms":102.09212},{"min":0,"max":93,"rms":67.14015},{"min":-5,"max":7,"rms":4.732864},{"min":0,"max":138,"rms":85.50088},{"min":0,"max":217,"rms":177.06213},{"min":0,"max":190,"rms":151.30301},{"min":0,"max":83,"rms":51.911465},{"min":-238,"max":75,"rms":140.3232},{"min":-455,"max":0,"rms":350.78738},{"min":-459,"max":0,"rms":341.36755},{"min":-158,"max":47,"rms":88.19297},{"min":0,"max":149,"rms":122.77948},{"min":0,"max":77,"rms":47.90616},{"min":0,"max":132,"rms":78.92021},{"min":0,"max":119,"rms":104.06536},{"min":0,"max":63,"rms":31.025795},{"min":-6,"max":37,"rms":19.646883},{"min":0,"max":172,"rms":124.51265},{"min":0,"max":177,"rms":146.75899},{"min":0,"max":85,"rms":57.846348},{"min":0,"max":28,"rms":24.543839},{"min":-221,"max":31,"rms":163.46681},{"min":-373,"max":0,"rms":323.72302},{"min":-270,"max":0,"rms":214.34085},{"min":-77,"max":62,"rms":53.064114},{"min":0,"max":96,"rms":68.96811},{"min":-2,"max":16,"rms":10.29563},{"min":0,"max":138,"rms":108.779594},{"min":0,"max":127,"rms":105.51493},{"min":0,"max":47,"rms":32.19938},{"min":0,"max":84,"rms":56.124863},{"min":0,"max":147,"rms":121.31117},{"min":0,"max":138,"rms":102.07154},{"min":-15,"max":41,"rms":23.353802},{"min":-21,"max":0,"rms":13.42386},{"min":-168,"max":13,"rms":100.509705},{"min":-276,"max":0,"rms":230.16255},{"min":-266,"max":0,"rms":201.342},{"min":-114,"max":0,"rms":75.26221},{"min":-14,"max":11,"rms":9.284395},{"min":0,"max":51,"rms":32.493076},{"min":0,"max":158,"rms":128.47957},{"min":0,"max":156,"rms":131.13428},{"min":0,"max":85,"rms":64.86139},{"min":0,"max":66,"rms":53.803345},{"min":0,"max":93,"rms":81.02222},{"min":0,"max":74,"rms":49.96799},{"min":-31,"max":6,"rms":23.456343},{"min":-50,"max":0,"rms":43.409676},{"min":-61,"max":0,"rms":49.305172},{"min":-152,"max":0,"rms":119.97583},{"min":-169,"max":0,"rms":156.57266},{"min":-139,"max":0,"rms":121.08757},{"min":-88,"max":0,"rms":58.96779},{"min":0,"max":79,"rms":52.581368},{"min":0,"max":156,"rms":122.72408},{"min":0,"max":162,"rms":158.44746},{"min":0,"max":149,"rms":124.41463},{"min":0,"max":77,"rms":56.231663},{"min":-13,"max":15,"rms":10.65833},{"min":-26,"max":0,"rms":17.815723},{"min":-28,"max":0,"rms":22.886677},{"min":-33,"max":0,"rms":26.784325},{"min":-34,"max":0,"rms":31.667017},{"min":-77,"max":0,"rms":57.30445},{"min":-152,"max":0,"rms":125.59459},{"min":-142,"max":0,"rms":127.05117},{"min":-99,"max":0,"rms":61.263367},{"min":0,"max":100,"rms":67.354286},{"min":0,"max":132,"rms":118.43817},{"min":0,"max":132,"rms":121.809685},{"min":0,"max":114,"rms":95.74863},{"min":0,"max":53,"rms":33.08776},{"min":-24,"max":0,"rms":16.27882},{"min":-30,"max":0,"rms":23.983328},{"min":-28,"max":0,"rms":22.569891},{"min":-40,"max":0,"rms":35.40339},{"min":-50,"max":0,"rms":46.735424},{"min":-74,"max":0,"rms":63.499607},{"min":-70,"max":0,"rms":61.106464},{"min":-50,"max":0,"rms":43.079},{"min":-37,"max":0,"rms":28.712368},{"min":-3,"max":22,"rms":11.74734},{"min":0,"max":75,"rms":49.185364},{"min":0,"max":98,"rms":87.01954},{"min":0,"max":92,"rms":79.16186},{"min":0,"max":57,"rms":43.099884},{"min":-4,"max":28,"rms":15.981238},{"min":-23,"max":0,"rms":14.58081},{"min":-29,"max":0,"rms":24.462215},{"min":-59,"max":0,"rms":48.528343},{"min":-65,"max":0,"rms":52.72381},{"min":-44,"max":0,"rms":36.994595},{"min":-36,"max":0,"rms":28.131832},{"min":-11,"max":3,"rms":6.371813},{"min":-7,"max":11,"rms":8.438009},{"min":0,"max":34,"rms":22.969545},{"min":0,"max":31,"rms":21.199057},{"min":0,"max":42,"rms":38.028934},{"min":0,"max":54,"rms":48.5963},{"min":0,"max":52,"rms":41.602886},{"min":0,"max":30,"rms":21.061813},{"min":-18,"max":0,"rms":11.9415245},{"min":-46,"max":0,"rms":43.28048},{"min":-58,"max":0,"rms":49.37813},{"min":-47,"max":0,"rms":42.270557},{"min":-31,"max":0,"rms":23.562683},{"min":-8,"max":0,"rms":6.884766},{"min":-13,"max":1,"rms":8.087027},{"min":-9,"max":8,"rms":5.98331},{"min":0,"max":23,"rms":14.744491},{"min":0,"max":25,"rms":19.078785},{"min":0,"max":21,"rms":18.110771},{"min":0,"max":30,"rms":20.885403},{"min":0,"max":25,"rms":17.42986},{"min":-2,"max":13,"rms":7.4027023},{"min":-21,"max":0,"rms":13.364131},{"min":-25,"max":0,"rms":19.110207},{"min":-27,"max":0,"rms":24.979992},{"min":-42,"max":0,"rms":34.348217},{"min":-25,"max":0,"rms":19.183327},{"min":-15,"max":13,"rms":10.139033},{"min":0,"max":19,"rms":16.413408},{"min":0,"max":23,"rms":19.364916},{"min":0,"max":27,"rms":20.875824},{"min":0,"max":19,"rms":14.886235},{"min":-14,"max":10,"rms":9.581232},{"min":-9,"max":5,"rms":5.138093},{"min":-7,"max":16,"rms":8.318653},{"min":0,"max":12,"rms":8.899438},{"min":-1,"max":9,"rms":4.7958317},{"min":-8,"max":4,"rms":4.816638},{"min":-23,"max":0,"rms":19.12067},{"min":-26,"max":0,"rms":19.55505},{"min":-15,"max":0,"rms":10.7703295},{"min":0,"max":9,"rms":4.494441},{"min":0,"max":25,"rms":17.905306},{"min":0,"max":32,"rms":28.393661},{"min":-8,"max":27,"rms":13.490738},{"min":-15,"max":7,"rms":7.98749},{"min":-6,"max":4,"rms":3.5777087},{"min":-2,"max":8,"rms":4.8373547},{"min":-19,"max":6,"rms":9.154234},{"min":-15,"max":0,"rms":10.334409},{"min":-19,"max":0,"rms":12.569805},{"min":-35,"max":0,"rms":30.49918},{"min":-30,"max":0,"rms":23.895607},{"min":-24,"max":0,"rms":13.863622},{"min":0,"max":10,"rms":6.5268674},{"min":0,"max":15,"rms":12.845233},{"min":0,"max":17,"rms":14.331782},{"min":0,"max":27,"rms":18.862661},{"min":0,"max":20,"rms":15.855598},{"min":0,"max":19,"rms":12.2147455},{"min":-5,"max":4,"rms":3.4058774},{"min":-11,"max":0,"rms":8.402381},{"min":-17,"max":0,"rms":11.523889},{"min":-22,"max":0,"rms":14.812157},{"min":-24,"max":0,"rms":19.585709},{"min":-23,"max":0,"rms":14.085453},{"min":-7,"max":3,"rms":4.09878},{"min":0,"max":11,"rms":8.694826},{"min":0,"max":13,"rms":7.98749},{"min":0,"max":19,"rms":14.60137},{"min":0,"max":19,"rms":12.457929},{"min":-2,"max":10,"rms":6.292853},{"min":-4,"max":6,"rms":3.3763885},{"min":0,"max":12,"rms":5.8821764},{"min":0,"max":9,"rms":6.0497932},{"min":-17,"max":0,"rms":11.3842},{"min":-23,"max":0,"rms":18.330303},{"min":-12,"max":0,"rms":6.870226},{"min":-15,"max":0,"rms":11.8490505},{"min":-13,"max":0,"rms":8.037413},{"min":-5,"max":7,"rms":4.1472883},{"min":0,"max":1,"rms":0.6324555},{"min":0,"max":5,"rms":4.289522},{"min":0,"max":12,"rms":7.4431176},{"min":-4,"max":9,"rms":4.7116876},{"min":-3,"max":3,"rms":2.6457512},{"min":0,"max":9,"rms":5.8991523},{"min":0,"max":14,"rms":10.65833},{"min":0,"max":10,"rms":7.071068},{"min":-10,"max":4,"rms":6.884766},{"min":-8,"max":4,"rms":4.816638},{"min":-16,"max":0,"rms":12.181953},{"min":-25,"max":0,"rms":20.454828},{"min":-16,"max":0,"rms":13.475904},{"min":-11,"max":4,"rms":6.8992753},{"min":0,"max":14,"rms":11.357817}]}