{"source_file":"./1_jackson_45.wav","sample_rate":8000,"bits":16,"samples_per_pixel":256,"time_duration":0.601125,"processed_time_duration":26.716666666666666,"samples_length":18,"samples":[{"min":-1209,"max":982,"rms":540.4229},{"min":-1943,"max":1750,"rms":870.4943},{"min":-3590,"max":2562,"rms":1495.5189},{"min":-5574,"max":4564,"rms":2333.7622},{"min":-6385,"max":5875,"rms":2888.3845},{"min":-7822,"max":5701,"rms":2848.2227},{"min":-8169,"max":5578,"rms":2822.1558},{"min":-11205,"max":7505,"rms":3402.4963},{"min":-10537,"max":7531,"rms":3276.0544},{"min":-11030,"max":6616,"rms":3368.0317},{"min":-9841,"max":7067,"rms":3725.2012},{"min":-8050,"max":7247,"rms":3108.2483},{"min":-5376,"max":3901,"rms":2623.1128},{"min":-3558,"max":3148,"rms":1982.0972},{"min":-3310,"max":2418,"rms":1661.3394},{"min":-2622,"max":1761,"rms":1100.2697},{"min":-684,"max":968,"rms":287.46133},{"min":-909,"max":792,"rms":369.9339}]}