{"source_file":"./7_theo_37.wav","sample_rate":8000,"bits":16,"samples_per_pixel":256,"time_duration":0.783125,"processed_time_duration":26.104166666666669,"samples_length":24,"samples":[{"min":-135,"max":139,"rms":31.42184},{"min":-84,"max":85,"rms":16.955133},{"min":-54,"max":41,"rms":17.21146},{"min":-34,"max":24,"rms":10.188267},{"min":-14,"max":23,"rms":7.659247},{"min":-186,"max":86,"rms":21.338785},{"min":-24,"max":24,"rms":9.449495},{"min":-21,"max":25,"rms":8.150681},{"min":-22,"max":21,"rms":8.002441},{"min":-26,"max":23,"rms":8.450915},{"min":-21,"max":19,"rms":7.8883815},{"min":-19,"max":19,"rms":6.9273577},{"min":-23,"max":18,"rms":7.568696},{"min":-24,"max":27,"rms":8.593921},{"min":-77,"max":81,"rms":23.247648},{"min":-72,"max":75,"rms":29.53368},{"min":-129,"max":138,"rms":43.549946},{"min":-940,"max":1547,"rms":308.98587},{"min":-1816,"max":2327,"rms":928.11536},{"min":-1281,"max":1830,"rms":607.0522},{"min":-414,"max":527,"rms":165.96829},{"min":-557,"max":568,"rms":188.63461},{"min":-498,"max":421,"rms":174.46732},{"min":-223,"max":180,"rms":73.25485}]}