{"source_file":"./4_jackson_21.wav","sample_rate":8000,"bits":16,"samples_per_pixel":256,"time_duration":0.35475,"processed_time_duration":25.8,"samples_length":11,"samples":[{"min":-10988,"max":10454,"rms":3920.422},{"min":-14046,"max":14635,"rms":6388.8335},{"min":-12591,"max":15524,"rms":6088.954},{"min":-11365,"max":14802,"rms":5004.122},{"min":-9972,"max":11049,"rms":4169.298},{"min":-6204,"max":6762,"rms":2388.33},{"min":-4935,"max":5663,"rms":2057.3948},{"min":-2677,"max":3687,"rms":1276.844},{"min":-2490,"max":2566,"rms":816.41516},{"min":-972,"max":1433,"rms":537.3893},{"min":-875,"max":995,"rms":359.5046}]}